hlbc-0.5.0.dist-info/METADATA
hlbc-0.5.0.dist-info/WHEEL
hlbc-0.5.0.dist-info/license_files/LICENSE
hlbc/__init__.py
hlbc/hlbc.cp310-win_amd64.pyd
hlbc-0.5.0.dist-info/RECORD
