Metadata-Version: 2.3
Name: hlbc
Version: 0.5.0
Classifier: Development Status :: 3 - Alpha
Classifier: License :: OSI Approved :: MIT License
Classifier: Programming Language :: Python :: 3.10
License-File: LICENSE
Summary: A (terrible) Python wrapper for hlbc
Keywords: haxe,hashlink,decompiler,disassembler,hlbc
Maintainer-email: N3rdL0rd <n3rdl0rd@proton.me>
Requires-Python: >=3.10
Project-URL: homepage, https://github.com/N3rdL0rd/hlbc-python
Project-URL: repository, https://github.com/N3rdL0rd/hlbc-python
